ghNum/__init__.py
ghnum-1.1.3.dist-info/METADATA
ghnum-1.1.3.dist-info/WHEEL
ghnum-1.1.3.dist-info/top_level.txt
ghnum-1.1.3.dist-info/RECORD
