Metadata-Version: 2.4
Name: ghNum
Version: 1.1.3
Summary: Professional Persian text to number converter
Author-email: Ghasem Jahed <ghasem.jahed2008@gmail.com>
License: MIT
